easyrpc/__init__.py
easyrpc/auth.py
easyrpc/exceptions.py
easyrpc/generator.py
easyrpc/origin.py
easyrpc/proxy.py
easyrpc/register.py
easyrpc/server.py
easyrpc/tools/__init__.py
easyrpc/tools/database.py
easyrpc/tools/logger.py
easyrpc-0.244.dist-info/LICENSE.MD
easyrpc-0.244.dist-info/METADATA
easyrpc-0.244.dist-info/WHEEL
easyrpc-0.244.dist-info/top_level.txt
easyrpc-0.244.dist-info/RECORD
