Metadata-Version: 2.1
Name: easyrpc
Version: 0.244
Summary: An easy to use rpc framework for enabling fast inter-process, inter-host communication
Home-page: https://github.com/codemation/easyrpc
Author: Joshua Jamison
Author-email: joshjamison1@gmail.com
License: UNKNOWN
Platform: UNKNOWN
Classifier: Programming Language :: Python :: 3
Classifier: License :: OSI Approved :: MIT License
Classifier: Operating System :: OS Independent
Requires-Python: >=3.7, <4
Requires-Dist: makefun (==1.9.5)
Requires-Dist: PyJWT (==2.0.0)
Requires-Dist: fastapi
Requires-Dist: uvicorn
Requires-Dist: websockets
Requires-Dist: aiohttp
